physicX/__init__.py
physicX/constants.py
physicX/law.py
physicX/mathlib.py
physicX-0.0.11927.dist-info/METADATA
physicX-0.0.11927.dist-info/WHEEL
physicX-0.0.11927.dist-info/top_level.txt
physicX-0.0.11927.dist-info/RECORD
