Metadata-Version: 2.1
Name: physicX
Version: 0.0.11927
Summary: mathematics and physics library
Author-email: anonymous14725 <anonymous14725@yahoo.com>
Project-URL: Homepage, https://github.com/anonymous14725/physicX
Project-URL: Bug Tracker, https://github.com/anonymous14725/physicX/issues
Classifier: Programming Language :: Python :: 3
Classifier: License :: OSI Approved :: GNU General Public License v3 (GPLv3)
Classifier: Operating System :: Other OS
Classifier: Environment :: GPU :: NVIDIA CUDA
Requires-Python: >=3.7
Requires-Dist: numpy >=1.24.2
Requires-Dist: setuptools >=61.0
